kearsley/__init__.py
kearsley/kearsley.py
kearsley/tests/__init__.py
kearsley/tests/test_kearsley.py
kearsley-0.2.0.dist-info/LICENSE
kearsley-0.2.0.dist-info/WHEEL
kearsley-0.2.0.dist-info/METADATA
kearsley-0.2.0.dist-info/RECORD
