Metadata-Version: 2.1
Name: kearsley
Version: 0.2.0
Summary: Structural comparison of 3D points
License: MIT
Author: Marcelo Moreno
Author-email: marcelo.moreno.suarez@gmail.com
Requires-Python: >=3.8,<4.0
Classifier: License :: OSI Approved :: MIT License
Classifier: Programming Language :: Python :: 3
Classifier: Programming Language :: Python :: 3.10
Classifier: Programming Language :: Python :: 3.8
Classifier: Programming Language :: Python :: 3.9
Requires-Dist: numpy (>=1.19.2,<2.0.0)
Requires-Dist: pytest (>=6.1.1,<7.0.0)
Requires-Dist: scipy (>=1.6.1,<2.0.0)
